Metadata-Version: 2.1
Name: odoo-addon-shopfloor_batch_automatic_creation
Version: 18.0.1.0.0.2
Requires-Python: >=3.10
Requires-Dist: odoo-addon-shopfloor==18.0.*
Requires-Dist: odoo-addon-stock_picking_batch_creation==18.0.*
Requires-Dist: odoo==18.0.*
Summary: Create batch transfers for Cluster Picking
Home-page: https://github.com/OCA/stock-logistics-shopfloor
License: AGPL-3
Author: Camptocamp, Odoo Community Association (OCA)
Author-email: support@odoo-community.org
Classifier: Programming Language :: Python
Classifier: Framework :: Odoo
Classifier: Framework :: Odoo :: 18.0
Classifier: License :: OSI Approved :: GNU Affero General Public License v3
